smafile/__init__.py
smafile/__main__.py
smafile-0.4.3.dist-info/LICENSE
smafile-0.4.3.dist-info/METADATA
smafile-0.4.3.dist-info/WHEEL
smafile-0.4.3.dist-info/top_level.txt
smafile-0.4.3.dist-info/RECORD
