Metadata-Version: 2.1
Name: smafile
Version: 0.4.3
Summary: parse smali file
Home-page: https://github.com/mikusjelly/smafile
Author: mikusjelly
Author-email: mikusjelly@gmail.com
License: MIT
Keywords: smali
Platform: UNKNOWN
Classifier: Development Status :: 4 - Beta
Classifier: License :: OSI Approved :: MIT License
Classifier: Programming Language :: Python :: 3 :: Only
Classifier: Topic :: Utilities
